go_hotspot_socks_proxy-1.2.0.dist-info/METADATA
go_hotspot_socks_proxy-1.2.0.dist-info/WHEEL
go_hotspot_socks_proxy-1.2.0.dist-info/entry_points.txt
go_hotspot_socks_proxy/__init__.py
go_hotspot_socks_proxy/cmd/__init__.py
go_hotspot_socks_proxy/cmd/cli.py
go_hotspot_socks_proxy/cmd/find_wifi.py
go_hotspot_socks_proxy/cmd/http.py
go_hotspot_socks_proxy/cmd/socks.py
go_hotspot_socks_proxy/core/__init__.py
go_hotspot_socks_proxy/core/network.py
go_hotspot_socks_proxy/core/proxy.py
go_hotspot_socks_proxy-1.2.0.dist-info/RECORD
