Metadata-Version: 2.1
Name: go-hotspot-socks-proxy
Version: 1.2.0
Summary: SOCKS proxy for routing traffic through WiFi interface
Author-Email: tadeasf <business@tadeasfort.com>
Requires-Python: >=3.12
Requires-Dist: typer>=0.15.1
Requires-Dist: prompt-toolkit>=3.0.48
Requires-Dist: rich>=13.9.4
Requires-Dist: psutil>=6.1.0
Requires-Dist: pyperclip>=1.9.0
Requires-Dist: dnspython>=2.7.0
